aeb43/AEB43.txt
aeb43/__init__.py
aeb43/test.py
aeb43/test_readme.py
aeb43-0.1.1.dist-info/METADATA
aeb43-0.1.1.dist-info/WHEEL
aeb43-0.1.1.dist-info/top_level.txt
aeb43-0.1.1.dist-info/RECORD
