Metadata-Version: 2.1
Name: aeb43
Version: 0.1.1
Summary: A module to parse AEB43 files
Home-page: https://pypi.org/project/aeb43/
Download-URL: https://downloads.tryton.org/aeb43/
Author: Tryton
Author-email: foundation@tryton.org
License: BSD
Project-URL: Bug Tracker, https://bugs.tryton.org/aeb43
Project-URL: Forum, https://discuss.tryton.org/tags/aeb43
Project-URL: Source Code, https://code.tryton.org/aeb43
Keywords: AEB43 parser
Classifier: Intended Audience :: Developers
Classifier: License :: OSI Approved :: BSD License
Classifier: Operating System :: OS Independent
Classifier: Programming Language :: Python :: 3
Classifier: Programming Language :: Python :: 3.8
Classifier: Programming Language :: Python :: 3.9
Classifier: Programming Language :: Python :: 3.10
Classifier: Programming Language :: Python :: 3.11
Classifier: Programming Language :: Python :: 3.12
Classifier: Topic :: Office/Business
Classifier: Topic :: Software Development :: Libraries
Classifier: Topic :: Utilities
Requires-Python: >=3.8
Requires-Dist: python-stdnum
